peglib/__init__.py
peglib/__main__.py
peglib/cli.py
peglib/py.typed
peglib-0.0.0.dist-info/LICENSE
peglib-0.0.0.dist-info/METADATA
peglib-0.0.0.dist-info/WHEEL
peglib-0.0.0.dist-info/entry_points.txt
peglib-0.0.0.dist-info/top_level.txt
peglib-0.0.0.dist-info/RECORD
